mjaf/__init__.py
mjaf/_utils/__init__.py
mjaf/_utils/constants.py
mjaf/_utils/paths.py
mjaf/logging/__init__.py
mjaf/logging/_core.py
mjaf-0.3.0.dist-info/licenses/LICENSE
mjaf-0.3.0.dist-info/METADATA
mjaf-0.3.0.dist-info/WHEEL
mjaf-0.3.0.dist-info/entry_points.txt
mjaf-0.3.0.dist-info/top_level.txt
mjaf-0.3.0.dist-info/RECORD
