Metadata-Version: 2.4
Name: mjaf
Version: 0.3.0
Summary: A collection of assorted utilites
Author-email: Max Fatouros <git.dzh5i@simplelogin.com>
Project-URL: Changelog, https://github.com/max-fatouros/mjaf/blob/main/CHANGELOG.md
Project-URL: Homepage, https://github.com/max-fatouros/mjaf
Project-URL: Issues, https://github.com/max-fatouros/mjaf/issues
Classifier: License :: OSI Approved :: MIT License
Classifier: Programming Language :: Python :: 3
Requires-Python: >=3.10
License-File: LICENSE
Requires-Dist: rich
Provides-Extra: dev
Requires-Dist: pre-commit; extra == "dev"
Requires-Dist: pytest; extra == "dev"
Dynamic: license-file
